erroremailer/__init__.py
erroremailer/send_email.py
error_emailer-0.1.2.dist-info/LICENSE
error_emailer-0.1.2.dist-info/METADATA
error_emailer-0.1.2.dist-info/WHEEL
error_emailer-0.1.2.dist-info/top_level.txt
error_emailer-0.1.2.dist-info/RECORD
