Metadata-Version: 2.1
Name: error-emailer
Version: 0.1.2
Summary: auto emailer
Home-page: https://github.com/stvgz/error-emailer
Author: Stvgz
Author-email: zhitao.gao@outlook.com
License: UNKNOWN
Project-URL: Bug Tracker, https://github.com/stvgz/error-emailer/issues
Platform: UNKNOWN
Classifier: Programming Language :: Python :: 3
Classifier: License :: OSI Approved :: MIT License
Classifier: Operating System :: OS Independent
License-File: LICENSE
